dsi_schema_assurance/__init__.py
dsi_schema_assurance/detectors/__init__.py
dsi_schema_assurance/detectors/ontology.py
dsi_schema_assurance/detectors/shacl.py
dsi_schema_assurance/injector.py
dsi_schema_assurance/utils/__init__.py
dsi_schema_assurance/utils/ddl/__init__.py
dsi_schema_assurance/utils/ddl/cim.py
dsi_schema_assurance/utils/ddl/default.py
dsi_schema_assurance/utils/ddl/dl.py
dsi_schema_assurance/utils/pandas.py
dsi_schema_assurance/validator.py
dsi_schema_assurance-1.0.4.dist-info/LICENSE
dsi_schema_assurance-1.0.4.dist-info/WHEEL
dsi_schema_assurance-1.0.4.dist-info/METADATA
dsi_schema_assurance-1.0.4.dist-info/RECORD
