Metadata-Version: 2.1
Name: dsi-schema-assurance
Version: 1.0.4
Summary: Package for schema assurance.
License: Apache-2.0
Author: Joao Nisa
Author-email: joao.nisa@mesh-ai.com
Requires-Python: >=3.10,<4.0
Classifier: License :: OSI Approved :: Apache Software License
Classifier: Programming Language :: Python :: 3
Classifier: Programming Language :: Python :: 3.10
Classifier: Programming Language :: Python :: 3.11
Requires-Dist: opentelemetry-api (==1.29.0)
Requires-Dist: pyshacl (<=0.29.0)
Requires-Dist: rdflib (<=7.1.1)
Requires-Dist: requests (==2.32.3)
Requires-Dist: setuptools (==68.2.2)
